.DS_Store
open-datagen/__init__.py
open-datagen/data_manager.py
opendatagen/__init__.py
opendatagen/agent.py
opendatagen/anonymizer.py
opendatagen/data_generator.py
opendatagen/data_manager.py
opendatagen/main.py
opendatagen/model.py
opendatagen/template.py
opendatagen/utils.py
opendatagen/files/basic.txt
opendatagen/files/breath.txt
opendatagen/files/breath_evol_instruct.txt
opendatagen/files/completion.txt
opendatagen/files/concretizing.txt
opendatagen/files/deep.txt
opendatagen/files/deepening.txt
opendatagen/files/deepening_evol_instruct.txt
opendatagen/files/difficulty_scorer_evol_instruct.txt
opendatagen/files/evol_instruct.txt
opendatagen/files/generation.txt
opendatagen/files/ner.txt
opendatagen/files/scorer.txt
opendatagen/files/step-reasoning_evol_instruct.txt
opendatagen/files/step_reasoning.txt
opendatagen/files/template.json
opendatagen-0.0.34.dist-info/LICENCE.md
opendatagen-0.0.34.dist-info/METADATA
opendatagen-0.0.34.dist-info/WHEEL
opendatagen-0.0.34.dist-info/top_level.txt
opendatagen-0.0.34.dist-info/RECORD
