Metadata-Version: 2.1
Name: opendatagen
Version: 0.0.34
Summary: Data preparation system to build controllable AI system
Home-page: https://github.com/thoddnn/open-datagen
Author: Thomas DORDONNE
Author-email: dordonne.thomas@gmail.com
License: UNKNOWN
Platform: UNKNOWN
Requires-Dist: openai (==1.5.0)
Requires-Dist: python-dotenv (>=0.17.1)
Requires-Dist: numpy (>=1.23.4)
Requires-Dist: trafilatura (>=0.9.1)
Requires-Dist: requests (>=2.29.0)
Requires-Dist: tenacity (>=8.2.2)
Requires-Dist: pydantic (>=2)
Requires-Dist: spacy (>=3)
Requires-Dist: tiktoken (>=0.5)
Requires-Dist: PyPDF2 (>=3)
Requires-Dist: pandas (>=2)
Requires-Dist: datasets (>=2)
Requires-Dist: mistralai
Requires-Dist: jsonschema
Requires-Dist: llama-cpp-python (>=0.2.24)
Requires-Dist: openai-whisper
Requires-Dist: elevenlabs (==0.3.0b0)
Requires-Dist: Pillow
Requires-Dist: torch (==2.1.0)
Requires-Dist: audiocraft
